pytmi/__init__.py
pytmi/client.py
pytmi/common.py
pytmi/message.py
pytmi/stream.py
pytmi-1.0.0.dist-info/LICENSE
pytmi-1.0.0.dist-info/METADATA
pytmi-1.0.0.dist-info/WHEEL
pytmi-1.0.0.dist-info/top_level.txt
pytmi-1.0.0.dist-info/RECORD
