Metadata-Version: 2.1
Name: pytmi
Version: 1.0.0
Summary: TMI (Twitch Messaging Interface) library for Python.
Home-page: https://github.com/bynect/pytmi
Author: nect
Classifier: Programming Language :: Python :: 3.7
Classifier: Programming Language :: Python :: 3.8
Classifier: Programming Language :: Python :: 3.9
Classifier: Programming Language :: Python :: 3.10
Classifier: Programming Language :: Python :: 3.11
Classifier: License :: OSI Approved :: MIT License
Classifier: Operating System :: OS Independent
Requires-Python: >= 3.7
License-File: LICENSE
